psychoanalyze/__init__.py
psychoanalyze/analysis/__init__.py
psychoanalyze/analysis/bayes.py
psychoanalyze/analysis/ecdf.py
psychoanalyze/analysis/strength_duration.py
psychoanalyze/analysis/weber.py
psychoanalyze/dashboard/__init__.py
psychoanalyze/dashboard/app.py
psychoanalyze/dashboard/assets/PsychoAnalyze.svg
psychoanalyze/dashboard/assets/PsychoAnalyze_350x350.png
psychoanalyze/dashboard/assets/favicon.ico
psychoanalyze/dashboard/assets/logo_bgwhite.png
psychoanalyze/dashboard/assets/logo_transparent_100x100.png
psychoanalyze/dashboard/assets/styles.css
psychoanalyze/dashboard/components.py
psychoanalyze/dashboard/layout.py
psychoanalyze/dashboard/utils.py
psychoanalyze/data/__init__.py
psychoanalyze/data/blocks.py
psychoanalyze/data/logistic.py
psychoanalyze/data/points.py
psychoanalyze/data/sessions.py
psychoanalyze/data/stimulus.py
psychoanalyze/data/subjects.py
psychoanalyze/data/trials.py
psychoanalyze/data/types.py
psychoanalyze/main.py
psychoanalyze/params.py
psychoanalyze/plot.py
psychoanalyze/sigmoids.py
psychoanalyze-0.8.9.dist-info/LICENSE
psychoanalyze-0.8.9.dist-info/METADATA
psychoanalyze-0.8.9.dist-info/WHEEL
psychoanalyze-0.8.9.dist-info/entry_points.txt
psychoanalyze-0.8.9.dist-info/RECORD
