Metadata-Version: 2.1
Name: psychoanalyze
Version: 0.8.9
Summary: Interactive analysis and simulation of psychophysical data.
Home-page: https://psychoanalyze.io
License: GPL-3.0-or-later
Keywords: psychophysics,neuroscience,psychology
Author: Ty Schlichenmeyer
Author-email: t.schlic@wustl.edu
Requires-Python: >=3.9.0,<3.12.0
Classifier: Development Status :: 3 - Alpha
Classifier: Environment :: Web Environment
Classifier: Framework :: Dash
Classifier: Intended Audience :: Science/Research
Classifier: License :: OSI Approved :: GNU General Public License v3 or later (GPLv3+)
Classifier: Natural Language :: English
Classifier: Programming Language :: Python :: 3
Classifier: Programming Language :: Python :: 3.9
Classifier: Programming Language :: Python :: 3.10
Classifier: Programming Language :: Python :: 3.11
Classifier: Topic :: Scientific/Engineering :: Information Analysis
Classifier: Topic :: Scientific/Engineering :: Medical Science Apps.
Classifier: Topic :: Scientific/Engineering :: Visualization
Requires-Dist: click (>=8.1.3,<9.0.0)
Requires-Dist: dash (>=2.11.1,<3.0.0)
Requires-Dist: dash-bootstrap-components (>=1.4.1,<2.0.0)
Requires-Dist: duckdb (>=0.8.1,<0.9.0)
Requires-Dist: gunicorn (>=20.1.0,<21.0.0)
Requires-Dist: kaleido (==0.2.1)
Requires-Dist: numpy (>=1.25.0,<2.0.0)
Requires-Dist: pandas (>=2.0.2,<3.0.0)
Requires-Dist: pandera (>=0.15.1,<0.16.0)
Requires-Dist: pyarrow (>=12.0.1,<13.0.0)
Requires-Dist: scikit-learn (>=1.2.2,<2.0.0)
Requires-Dist: scipy (>=1.10.1,<2.0.0)
Requires-Dist: statsmodels (>=0.14.0,<0.15.0)
Requires-Dist: typer[all] (>=0.9.0,<0.10.0)
Project-URL: Documentation, https://docs.psychoanalyze.io
Project-URL: JupyterHub, https://nb.psychoanalyze.io
Project-URL: Repository, https://github.com/psychoanalyze/psychoanalyze
